<solutionSettings>
    <callStackOpen value="false"/>
    <localsViewOpen value="false"/>
    <openFiles>
        <item value="C:/work/cmajor-mod/cmajor/masm/system/System.Base/Conversion.cm"/>
        <item value="C:/work/cmajor-mod/cmajor/masm/system/System.XPath/XPathEvaluate.cm"/>
    </openFiles>
    <currentOpenFile value="C:/work/cmajor-mod/cmajor/masm/system/System.XPath/XPathEvaluate.cm"/>
    <currentCursorLine value="103"/>
    <breakpoints/>
    <expandedProjects>
        <item value="System.XPath"/>
    </expandedProjects>
</solutionSettings>
